imagecorruptions/__init__.py
imagecorruptions/corruptions.py
imagecorruptions/frost/frost1.png
imagecorruptions/frost/frost2.png
imagecorruptions/frost/frost3.png
imagecorruptions/frost/frost4.jpg
imagecorruptions/frost/frost5.jpg
imagecorruptions/frost/frost6.jpg
imagecorruptions-1.1.2.dist-info/LICENSE
imagecorruptions-1.1.2.dist-info/METADATA
imagecorruptions-1.1.2.dist-info/WHEEL
imagecorruptions-1.1.2.dist-info/top_level.txt
imagecorruptions-1.1.2.dist-info/RECORD
