Metadata-Version: 2.1
Name: imagecorruptions
Version: 1.1.2
Summary: This package provides a set of image corruptions.
Home-page: https://github.com/bethgelab/imagecorruptions
Author: Evgenia Rusak, Benjamin Mitzkus
Author-email: evgenia.rusak@bethgelab.org, benjamin.mitzkus@bethgelab.org
License: UNKNOWN
Platform: UNKNOWN
Classifier: Programming Language :: Python :: 3
Classifier: License :: OSI Approved :: Apache Software License
Classifier: Operating System :: OS Independent
